mechanician/__init__.py
mechanician/ai_connectors.py
mechanician/ai_tools.py
mechanician/instruction_tuning.py
mechanician/shell.py
mechanician/tagai.py
mechanician/testing.py
mechanician/util.py
mechanician/tools/__init__.py
mechanician/tools/notepads.py
mechanician/tools/workflows.py
mechanician-0.1.3.dist-info/METADATA
mechanician-0.1.3.dist-info/WHEEL
mechanician-0.1.3.dist-info/top_level.txt
mechanician-0.1.3.dist-info/RECORD
