Metadata-Version: 2.1
Name: mechanician
Version: 0.1.3
Summary: Building tools that use AI by building tools that AIs use.
Home-page: https://github.com/liebke/mechanician
Author: David Edgar Liebke
Author-email: david@gmail.com
Requires-Dist: rich >=10.0.0
